<response>
  <status>success</status>
  <items_returned>20</items_returned>
  <items_available>1664</items_available>
  <first_item_position>440</first_item_position>
  <result>
    <contributor_fact>
      <contributor_id>2530596878407052</contributor_id>
      <analysis_id>29312807</analysis_id>
      <contributor_name>Kevin Murphy</contributor_name>
      <primary_language_id>102</primary_language_id>
      <primary_language_nice_name>Rust</primary_language_nice_name>
      <comment_ratio>0.0775193798449612</comment_ratio>
      <first_commit_time>2013-07-23T00:00:00Z</first_commit_time>
      <last_commit_time>2013-07-25T00:00:00Z</last_commit_time>
      <man_months>1</man_months>
      <commits>5</commits>
    </contributor_fact>
    <contributor_fact>
      <contributor_id>2530596879182231</contributor_id>
      <analysis_id>29312807</analysis_id>
      <contributor_name>parir</contributor_name>
      <primary_language_id>102</primary_language_id>
      <primary_language_nice_name>Rust</primary_language_nice_name>
      <comment_ratio />
      <first_commit_time>2015-05-14T00:00:00Z</first_commit_time>
      <last_commit_time>2015-05-19T00:00:00Z</last_commit_time>
      <man_months>1</man_months>
      <commits>5</commits>
    </contributor_fact>
    <contributor_fact>
      <contributor_id>2530596878793489</contributor_id>
      <analysis_id>29312807</analysis_id>
      <contributor_name>Christopher Chambers</contributor_name>
      <primary_language_id>102</primary_language_id>
      <primary_language_nice_name>Rust</primary_language_nice_name>
      <comment_ratio>0.125</comment_ratio>
      <first_commit_time>2015-04-07T00:00:00Z</first_commit_time>
      <last_commit_time>2015-04-11T00:00:00Z</last_commit_time>
      <man_months>1</man_months>
      <commits>5</commits>
    </contributor_fact>
    <contributor_fact>
      <contributor_id>2530596878634904</contributor_id>
      <analysis_id>29312807</analysis_id>
      <contributor_name>Raphael Speyer</contributor_name>
      <primary_language_id>102</primary_language_id>
      <primary_language_nice_name>Rust</primary_language_nice_name>
      <comment_ratio>0.0950704225352113</comment_ratio>
      <first_commit_time>2013-12-09T00:00:00Z</first_commit_time>
      <last_commit_time>2015-04-20T00:00:00Z</last_commit_time>
      <man_months>4</man_months>
      <commits>5</commits>
    </contributor_fact>
    <contributor_fact>
      <contributor_id>2530596878654937</contributor_id>
      <analysis_id>29312807</analysis_id>
      <contributor_name>Damien Radtke</contributor_name>
      <primary_language_id>48</primary_language_id>
      <primary_language_nice_name>Vim Script</primary_language_nice_name>
      <comment_ratio />
      <first_commit_time>2014-09-22T00:00:00Z</first_commit_time>
      <last_commit_time>2014-11-04T00:00:00Z</last_commit_time>
      <man_months>3</man_months>
      <commits>5</commits>
    </contributor_fact>
    <contributor_fact>
      <contributor_id>2530596878791427</contributor_id>
      <analysis_id>29312807</analysis_id>
      <contributor_name>Margaret Meyerhofer</contributor_name>
      <primary_language_id>102</primary_language_id>
      <primary_language_nice_name>Rust</primary_language_nice_name>
      <comment_ratio>0.0417362270450751</comment_ratio>
      <first_commit_time>2012-05-23T00:00:00Z</first_commit_time>
      <last_commit_time>2012-05-23T00:00:00Z</last_commit_time>
      <man_months>1</man_months>
      <commits>5</commits>
    </contributor_fact>
    <contributor_fact>
      <contributor_id>2530596879007248</contributor_id>
      <analysis_id>29312807</analysis_id>
      <contributor_name>Dave Hodder</contributor_name>
      <primary_language_id>102</primary_language_id>
      <primary_language_nice_name>Rust</primary_language_nice_name>
      <comment_ratio />
      <first_commit_time>2013-11-17T00:00:00Z</first_commit_time>
      <last_commit_time>2016-01-16T00:00:00Z</last_commit_time>
      <man_months>3</man_months>
      <commits>5</commits>
    </contributor_fact>
    <contributor_fact>
      <contributor_id>2530596879129213</contributor_id>
      <analysis_id>29312807</analysis_id>
      <contributor_name>Cristian Kubis</contributor_name>
      <primary_language_id>6</primary_language_id>
      <primary_language_nice_name>JavaScript</primary_language_nice_name>
      <comment_ratio />
      <first_commit_time>2015-01-08T00:00:00Z</first_commit_time>
      <last_commit_time>2015-10-01T00:00:00Z</last_commit_time>
      <man_months>3</man_months>
      <commits>5</commits>
    </contributor_fact>
    <contributor_fact>
      <contributor_id>2530596878903297</contributor_id>
      <analysis_id>29312807</analysis_id>
      <contributor_name>Vitali Haravy</contributor_name>
      <primary_language_id>51</primary_language_id>
      <primary_language_nice_name>Autoconf</primary_language_nice_name>
      <comment_ratio />
      <first_commit_time>2014-11-05T00:00:00Z</first_commit_time>
      <last_commit_time>2015-09-17T00:00:00Z</last_commit_time>
      <man_months>2</man_months>
      <commits>5</commits>
    </contributor_fact>
    <contributor_fact>
      <contributor_id>2530596879255526</contributor_id>
      <analysis_id>29312807</analysis_id>
      <contributor_name>Steven Burns</contributor_name>
      <primary_language_id>9</primary_language_id>
      <primary_language_nice_name>Python</primary_language_nice_name>
      <comment_ratio />
      <first_commit_time>2016-05-13T00:00:00Z</first_commit_time>
      <last_commit_time>2016-06-04T00:00:00Z</last_commit_time>
      <man_months>1</man_months>
      <commits>5</commits>
    </contributor_fact>
    <contributor_fact>
      <contributor_id>2530596878633468</contributor_id>
      <analysis_id>29312807</analysis_id>
      <contributor_name>Ivan Ukhov</contributor_name>
      <primary_language_id>4</primary_language_id>
      <primary_language_nice_name>CSS</primary_language_nice_name>
      <comment_ratio />
      <first_commit_time>2014-10-15T00:00:00Z</first_commit_time>
      <last_commit_time>2015-07-12T00:00:00Z</last_commit_time>
      <man_months>4</man_months>
      <commits>5</commits>
    </contributor_fact>
    <contributor_fact>
      <contributor_id>2530596878795464</contributor_id>
      <analysis_id>29312807</analysis_id>
      <contributor_name>Markus Westerlind</contributor_name>
      <primary_language_id>102</primary_language_id>
      <primary_language_nice_name>Rust</primary_language_nice_name>
      <comment_ratio>0.601674641148325</comment_ratio>
      <first_commit_time>2015-06-04T00:00:00Z</first_commit_time>
      <last_commit_time>2016-03-03T00:00:00Z</last_commit_time>
      <man_months>2</man_months>
      <commits>5</commits>
    </contributor_fact>
    <contributor_fact>
      <contributor_id>2530594730813153</contributor_id>
      <account_id>9953</account_id>
      <account_name>Sylvestre Ledru</account_name>
      <analysis_id>29312807</analysis_id>
      <contributor_name>Sylvestre Ledru</contributor_name>
      <primary_language_id>51</primary_language_id>
      <primary_language_nice_name>Autoconf</primary_language_nice_name>
      <comment_ratio />
      <first_commit_time>2014-06-05T00:00:00Z</first_commit_time>
      <last_commit_time>2016-07-03T00:00:00Z</last_commit_time>
      <man_months>3</man_months>
      <commits>5</commits>
    </contributor_fact>
    <contributor_fact>
      <contributor_id>2530596879241086</contributor_id>
      <analysis_id>29312807</analysis_id>
      <contributor_name>Daniel J Rollins</contributor_name>
      <primary_language_id>102</primary_language_id>
      <primary_language_nice_name>Rust</primary_language_nice_name>
      <comment_ratio />
      <first_commit_time>2016-03-05T00:00:00Z</first_commit_time>
      <last_commit_time>2016-03-06T00:00:00Z</last_commit_time>
      <man_months>1</man_months>
      <commits>5</commits>
    </contributor_fact>
    <contributor_fact>
      <contributor_id>2530596878749898</contributor_id>
      <analysis_id>29312807</analysis_id>
      <contributor_name>Paul Woolcock</contributor_name>
      <primary_language_id>102</primary_language_id>
      <primary_language_nice_name>Rust</primary_language_nice_name>
      <comment_ratio>0.0</comment_ratio>
      <first_commit_time>2012-01-30T00:00:00Z</first_commit_time>
      <last_commit_time>2016-07-26T00:00:00Z</last_commit_time>
      <man_months>2</man_months>
      <commits>5</commits>
    </contributor_fact>
    <contributor_fact>
      <contributor_id>2530594730831439</contributor_id>
      <account_id>28239</account_id>
      <account_name>Anders Kaseorg</account_name>
      <analysis_id>29312807</analysis_id>
      <contributor_name>Anders Kaseorg</contributor_name>
      <primary_language_id>102</primary_language_id>
      <primary_language_nice_name>Rust</primary_language_nice_name>
      <comment_ratio />
      <first_commit_time>2013-08-28T00:00:00Z</first_commit_time>
      <last_commit_time>2015-03-23T00:00:00Z</last_commit_time>
      <man_months>2</man_months>
      <commits>5</commits>
    </contributor_fact>
    <contributor_fact>
      <contributor_id>2530596878898803</contributor_id>
      <analysis_id>29312807</analysis_id>
      <contributor_name>Xuefeng Wu</contributor_name>
      <primary_language_id>102</primary_language_id>
      <primary_language_nice_name>Rust</primary_language_nice_name>
      <comment_ratio />
      <first_commit_time>2015-05-02T00:00:00Z</first_commit_time>
      <last_commit_time>2015-05-16T00:00:00Z</last_commit_time>
      <man_months>1</man_months>
      <commits>5</commits>
    </contributor_fact>
    <contributor_fact>
      <contributor_id>2530596878917958</contributor_id>
      <analysis_id>29312807</analysis_id>
      <contributor_name>=Mark Sinclair</contributor_name>
      <primary_language_id>102</primary_language_id>
      <primary_language_nice_name>Rust</primary_language_nice_name>
      <comment_ratio>0.0824295010845987</comment_ratio>
      <first_commit_time>2013-07-04T00:00:00Z</first_commit_time>
      <last_commit_time>2013-07-14T00:00:00Z</last_commit_time>
      <man_months>1</man_months>
      <commits>5</commits>
    </contributor_fact>
    <contributor_fact>
      <contributor_id>2530596878658437</contributor_id>
      <analysis_id>29312807</analysis_id>
      <contributor_name>Michael Rosenberg</contributor_name>
      <primary_language_id>102</primary_language_id>
      <primary_language_nice_name>Rust</primary_language_nice_name>
      <comment_ratio>0.102189781021898</comment_ratio>
      <first_commit_time>2015-04-24T00:00:00Z</first_commit_time>
      <last_commit_time>2016-07-13T00:00:00Z</last_commit_time>
      <man_months>2</man_months>
      <commits>5</commits>
    </contributor_fact>
    <contributor_fact>
      <contributor_id>2530594731274385</contributor_id>
      <account_id>471185</account_id>
      <account_name>Cynede</account_name>
      <analysis_id>29312807</analysis_id>
      <contributor_name>Heather</contributor_name>
      <primary_language_id>51</primary_language_id>
      <primary_language_nice_name>Autoconf</primary_language_nice_name>
      <comment_ratio>0.0</comment_ratio>
      <first_commit_time>2013-10-19T00:00:00Z</first_commit_time>
      <last_commit_time>2014-05-29T00:00:00Z</last_commit_time>
      <man_months>1</man_months>
      <commits>5</commits>
    </contributor_fact>
  </result>
</response>