<response>
  <status>success</status>
  <items_returned>16</items_returned>
  <items_available>16</items_available>
  <first_item_position>0</first_item_position>
  <result>
    <contributor_fact>
      <contributor_id>16041702859102</contributor_id>
      <account_id>8542</account_id>
      <account_name>hhuynh</account_name>
      <analysis_id>26658449</analysis_id>
      <contributor_name>hhuynh</contributor_name>
      <primary_language_id>3</primary_language_id>
      <primary_language_nice_name>XML</primary_language_nice_name>
      <comment_ratio>0.00775193798449612</comment_ratio>
      <first_commit_time>2011-07-04T00:00:00Z</first_commit_time>
      <last_commit_time>2014-07-18T00:00:00Z</last_commit_time>
      <man_months>16</man_months>
      <commits>37</commits>
    </contributor_fact>
    <contributor_fact>
      <contributor_id>16043850354359</contributor_id>
      <analysis_id>26658449</analysis_id>
      <contributor_name>teck</contributor_name>
      <primary_language_id>3</primary_language_id>
      <primary_language_nice_name>XML</primary_language_nice_name>
      <comment_ratio />
      <first_commit_time>2011-09-07T00:00:00Z</first_commit_time>
      <last_commit_time>2012-11-26T00:00:00Z</last_commit_time>
      <man_months>5</man_months>
      <commits>8</commits>
    </contributor_fact>
    <contributor_fact>
      <contributor_id>16041702858655</contributor_id>
      <account_id>8095</account_id>
      <account_name>Jason Voegele</account_name>
      <analysis_id>26658449</analysis_id>
      <contributor_name>jvoegele</contributor_name>
      <primary_language_id>3</primary_language_id>
      <primary_language_nice_name>XML</primary_language_nice_name>
      <comment_ratio />
      <first_commit_time>2011-10-26T00:00:00Z</first_commit_time>
      <last_commit_time>2013-04-23T00:00:00Z</last_commit_time>
      <man_months>5</man_months>
      <commits>5</commits>
    </contributor_fact>
    <contributor_fact>
      <contributor_id>16043850835473</contributor_id>
      <analysis_id>26658449</analysis_id>
      <contributor_name>adahanne</contributor_name>
      <primary_language_id>3</primary_language_id>
      <primary_language_nice_name>XML</primary_language_nice_name>
      <comment_ratio />
      <first_commit_time>2013-05-14T00:00:00Z</first_commit_time>
      <last_commit_time>2014-07-30T00:00:00Z</last_commit_time>
      <man_months>2</man_months>
      <commits>4</commits>
    </contributor_fact>
    <contributor_fact>
      <contributor_id>16043850619601</contributor_id>
      <analysis_id>26658449</analysis_id>
      <contributor_name>ljacomet</contributor_name>
      <primary_language_id>3</primary_language_id>
      <primary_language_nice_name>XML</primary_language_nice_name>
      <comment_ratio />
      <first_commit_time>2015-03-25T00:00:00Z</first_commit_time>
      <last_commit_time>2015-10-13T00:00:00Z</last_commit_time>
      <man_months>4</man_months>
      <commits>4</commits>
    </contributor_fact>
    <contributor_fact>
      <contributor_id>16043850359784</contributor_id>
      <analysis_id>26658449</analysis_id>
      <contributor_name>cruise</contributor_name>
      <primary_language_id>3</primary_language_id>
      <primary_language_nice_name>XML</primary_language_nice_name>
      <comment_ratio />
      <first_commit_time>2011-09-06T00:00:00Z</first_commit_time>
      <last_commit_time>2013-07-11T00:00:00Z</last_commit_time>
      <man_months>1</man_months>
      <commits>2</commits>
    </contributor_fact>
    <contributor_fact>
      <contributor_id>16043850671486</contributor_id>
      <analysis_id>26658449</analysis_id>
      <contributor_name>twu</contributor_name>
      <primary_language_id />
      <primary_language_nice_name />
      <comment_ratio />
      <first_commit_time>2011-11-30T00:00:00Z</first_commit_time>
      <last_commit_time>2011-11-30T00:00:00Z</last_commit_time>
      <man_months>0</man_months>
      <commits>1</commits>
    </contributor_fact>
    <contributor_fact>
      <contributor_id>16043851243920</contributor_id>
      <analysis_id>26658449</analysis_id>
      <contributor_name>akom</contributor_name>
      <primary_language_id>3</primary_language_id>
      <primary_language_nice_name>XML</primary_language_nice_name>
      <comment_ratio />
      <first_commit_time>2015-09-01T00:00:00Z</first_commit_time>
      <last_commit_time>2015-09-01T00:00:00Z</last_commit_time>
      <man_months>1</man_months>
      <commits>1</commits>
    </contributor_fact>
    <contributor_fact>
      <contributor_id>16041702989532</contributor_id>
      <account_id>138972</account_id>
      <account_name>abhisanoujam</account_name>
      <analysis_id>26658449</analysis_id>
      <contributor_name>asingh</contributor_name>
      <primary_language_id />
      <primary_language_nice_name />
      <comment_ratio />
      <first_commit_time>2011-09-10T00:00:00Z</first_commit_time>
      <last_commit_time>2011-09-10T00:00:00Z</last_commit_time>
      <man_months>0</man_months>
      <commits>1</commits>
    </contributor_fact>
    <contributor_fact>
      <contributor_id>16041702872244</contributor_id>
      <account_id>21684</account_id>
      <account_name>Ludovic Orban</account_name>
      <analysis_id>26658449</analysis_id>
      <contributor_name>lorban</contributor_name>
      <primary_language_id>3</primary_language_id>
      <primary_language_nice_name>XML</primary_language_nice_name>
      <comment_ratio />
      <first_commit_time>2012-02-15T00:00:00Z</first_commit_time>
      <last_commit_time>2012-02-15T00:00:00Z</last_commit_time>
      <man_months>1</man_months>
      <commits>1</commits>
    </contributor_fact>
    <contributor_fact>
      <contributor_id>16041702851376</contributor_id>
      <account_id>816</account_id>
      <account_name>saro</account_name>
      <analysis_id>0</analysis_id>
      <contributor_name />
      <primary_language_id>0</primary_language_id>
      <primary_language_nice_name />
      <comment_ratio>0</comment_ratio>
      <first_commit_time />
      <last_commit_time />
      <man_months>0</man_months>
      <commits>0</commits>
    </contributor_fact>
    <contributor_fact>
      <contributor_id>16041702861119</contributor_id>
      <account_id>10559</account_id>
      <account_name>Alex Snaps</account_name>
      <analysis_id>0</analysis_id>
      <contributor_name />
      <primary_language_id>0</primary_language_id>
      <primary_language_nice_name />
      <comment_ratio>0</comment_ratio>
      <first_commit_time />
      <last_commit_time />
      <man_months>0</man_months>
      <commits>0</commits>
    </contributor_fact>
    <contributor_fact>
      <contributor_id>16041702962489</contributor_id>
      <account_id>111929</account_id>
      <account_name>Manoj</account_name>
      <analysis_id>0</analysis_id>
      <contributor_name />
      <primary_language_id>0</primary_language_id>
      <primary_language_nice_name />
      <comment_ratio>0</comment_ratio>
      <first_commit_time />
      <last_commit_time />
      <man_months>0</man_months>
      <commits>0</commits>
    </contributor_fact>
    <contributor_fact>
      <contributor_id>16041702870965</contributor_id>
      <account_id>20405</account_id>
      <account_name>Alex Miller</account_name>
      <analysis_id>0</analysis_id>
      <contributor_name />
      <primary_language_id>0</primary_language_id>
      <primary_language_nice_name />
      <comment_ratio>0</comment_ratio>
      <first_commit_time />
      <last_commit_time />
      <man_months>0</man_months>
      <commits>0</commits>
    </contributor_fact>
    <contributor_fact>
      <contributor_id>16041702856863</contributor_id>
      <account_id>6303</account_id>
      <account_name>Eugene Kuleshov</account_name>
      <analysis_id>0</analysis_id>
      <contributor_name />
      <primary_language_id>0</primary_language_id>
      <primary_language_nice_name />
      <comment_ratio>0</comment_ratio>
      <first_commit_time />
      <last_commit_time />
      <man_months>0</man_months>
      <commits>0</commits>
    </contributor_fact>
    <contributor_fact>
      <contributor_id>16041702880693</contributor_id>
      <account_id>30133</account_id>
      <account_name>Chris Dennis</account_name>
      <analysis_id>0</analysis_id>
      <contributor_name />
      <primary_language_id>0</primary_language_id>
      <primary_language_nice_name />
      <comment_ratio>0</comment_ratio>
      <first_commit_time />
      <last_commit_time />
      <man_months>0</man_months>
      <commits>0</commits>
    </contributor_fact>
  </result>
</response>