<response>
  <status>success</status>
  <items_returned>20</items_returned>
  <items_available>809</items_available>
  <first_item_position>300</first_item_position>
  <result>
    <contributor_fact>
      <contributor_id>2064988063953240</contributor_id>
      <analysis_id>29311198</analysis_id>
      <contributor_name>Keith Goodman</contributor_name>
      <primary_language_id>9</primary_language_id>
      <primary_language_nice_name>Python</primary_language_nice_name>
      <comment_ratio />
      <first_commit_time>2011-05-19T00:00:00Z</first_commit_time>
      <last_commit_time>2015-10-14T00:00:00Z</last_commit_time>
      <man_months>2</man_months>
      <commits>3</commits>
    </contributor_fact>
    <contributor_fact>
      <contributor_id>2064988063788755</contributor_id>
      <analysis_id>29311198</analysis_id>
      <contributor_name>Julien Miotte</contributor_name>
      <primary_language_id>9</primary_language_id>
      <primary_language_nice_name>Python</primary_language_nice_name>
      <comment_ratio />
      <first_commit_time>2011-04-01T00:00:00Z</first_commit_time>
      <last_commit_time>2011-04-01T00:00:00Z</last_commit_time>
      <man_months>1</man_months>
      <commits>3</commits>
    </contributor_fact>
    <contributor_fact>
      <contributor_id>2064988064246780</contributor_id>
      <analysis_id>29311198</analysis_id>
      <contributor_name>Scott Dickerson</contributor_name>
      <primary_language_id>9</primary_language_id>
      <primary_language_nice_name>Python</primary_language_nice_name>
      <comment_ratio />
      <first_commit_time>2012-12-29T00:00:00Z</first_commit_time>
      <last_commit_time>2013-01-03T00:00:00Z</last_commit_time>
      <man_months>2</man_months>
      <commits>3</commits>
    </contributor_fact>
    <contributor_fact>
      <contributor_id>2064988064497924</contributor_id>
      <analysis_id>29311198</analysis_id>
      <contributor_name>Borja Ayerdi</contributor_name>
      <primary_language_id>9</primary_language_id>
      <primary_language_nice_name>Python</primary_language_nice_name>
      <comment_ratio />
      <first_commit_time>2014-11-20T00:00:00Z</first_commit_time>
      <last_commit_time>2014-11-27T00:00:00Z</last_commit_time>
      <man_months>1</man_months>
      <commits>3</commits>
    </contributor_fact>
    <contributor_fact>
      <contributor_id>2064988064146474</contributor_id>
      <analysis_id>29311198</analysis_id>
      <contributor_name>Mathieu Dubois</contributor_name>
      <primary_language_id>9</primary_language_id>
      <primary_language_nice_name>Python</primary_language_nice_name>
      <comment_ratio />
      <first_commit_time>2015-12-25T00:00:00Z</first_commit_time>
      <last_commit_time>2015-12-28T00:00:00Z</last_commit_time>
      <man_months>1</man_months>
      <commits>3</commits>
    </contributor_fact>
    <contributor_fact>
      <contributor_id>2064988064615307</contributor_id>
      <analysis_id>29311198</analysis_id>
      <contributor_name>hashcode55</contributor_name>
      <primary_language_id>9</primary_language_id>
      <primary_language_nice_name>Python</primary_language_nice_name>
      <comment_ratio />
      <first_commit_time>2016-06-18T00:00:00Z</first_commit_time>
      <last_commit_time>2016-06-19T00:00:00Z</last_commit_time>
      <man_months>1</man_months>
      <commits>3</commits>
    </contributor_fact>
    <contributor_fact>
      <contributor_id>2064988064582644</contributor_id>
      <analysis_id>29311198</analysis_id>
      <contributor_name>Andrew McCulloh</contributor_name>
      <primary_language_id>6</primary_language_id>
      <primary_language_nice_name>JavaScript</primary_language_nice_name>
      <comment_ratio />
      <first_commit_time>2015-11-16T00:00:00Z</first_commit_time>
      <last_commit_time>2015-11-16T00:00:00Z</last_commit_time>
      <man_months>1</man_months>
      <commits>3</commits>
    </contributor_fact>
    <contributor_fact>
      <contributor_id>2064988064574782</contributor_id>
      <analysis_id>29311198</analysis_id>
      <contributor_name>waterponey</contributor_name>
      <primary_language_id>11</primary_language_id>
      <primary_language_nice_name>shell script</primary_language_nice_name>
      <comment_ratio />
      <first_commit_time>2015-10-19T00:00:00Z</first_commit_time>
      <last_commit_time>2015-10-31T00:00:00Z</last_commit_time>
      <man_months>1</man_months>
      <commits>3</commits>
    </contributor_fact>
    <contributor_fact>
      <contributor_id>2064988064005125</contributor_id>
      <analysis_id>29311198</analysis_id>
      <contributor_name>Bryan Silverthorn</contributor_name>
      <primary_language_id>9</primary_language_id>
      <primary_language_nice_name>Python</primary_language_nice_name>
      <comment_ratio />
      <first_commit_time>2011-05-12T00:00:00Z</first_commit_time>
      <last_commit_time>2011-05-12T00:00:00Z</last_commit_time>
      <man_months>1</man_months>
      <commits>3</commits>
    </contributor_fact>
    <contributor_fact>
      <contributor_id>2064988064314738</contributor_id>
      <analysis_id>29311198</analysis_id>
      <contributor_name>Javier Lo&#769;pez Pen&#771;a</contributor_name>
      <primary_language_id>9</primary_language_id>
      <primary_language_nice_name>Python</primary_language_nice_name>
      <comment_ratio />
      <first_commit_time>2014-11-29T00:00:00Z</first_commit_time>
      <last_commit_time>2014-11-30T00:00:00Z</last_commit_time>
      <man_months>1</man_months>
      <commits>3</commits>
    </contributor_fact>
    <contributor_fact>
      <contributor_id>2064988064387692</contributor_id>
      <analysis_id>29311198</analysis_id>
      <contributor_name>Lukas Michelbacher</contributor_name>
      <primary_language_id>9</primary_language_id>
      <primary_language_nice_name>Python</primary_language_nice_name>
      <comment_ratio />
      <first_commit_time>2014-12-18T00:00:00Z</first_commit_time>
      <last_commit_time>2015-01-08T00:00:00Z</last_commit_time>
      <man_months>1</man_months>
      <commits>3</commits>
    </contributor_fact>
    <contributor_fact>
      <contributor_id>2064988064569424</contributor_id>
      <analysis_id>29311198</analysis_id>
      <contributor_name>Cindy Sridharan</contributor_name>
      <primary_language_id>9</primary_language_id>
      <primary_language_nice_name>Python</primary_language_nice_name>
      <comment_ratio />
      <first_commit_time>2015-07-11T00:00:00Z</first_commit_time>
      <last_commit_time>2015-09-13T00:00:00Z</last_commit_time>
      <man_months>2</man_months>
      <commits>3</commits>
    </contributor_fact>
    <contributor_fact>
      <contributor_id>2064988064497925</contributor_id>
      <analysis_id>29311198</analysis_id>
      <contributor_name>leepei</contributor_name>
      <primary_language_id>44</primary_language_id>
      <primary_language_nice_name>C++</primary_language_nice_name>
      <comment_ratio />
      <first_commit_time>2012-10-28T00:00:00Z</first_commit_time>
      <last_commit_time>2013-02-10T00:00:00Z</last_commit_time>
      <man_months>2</man_months>
      <commits>2</commits>
    </contributor_fact>
    <contributor_fact>
      <contributor_id>2064988063999532</contributor_id>
      <analysis_id>29311198</analysis_id>
      <contributor_name>Meng Xinfan</contributor_name>
      <primary_language_id>9</primary_language_id>
      <primary_language_nice_name>Python</primary_language_nice_name>
      <comment_ratio />
      <first_commit_time>2011-04-06T00:00:00Z</first_commit_time>
      <last_commit_time>2012-01-12T00:00:00Z</last_commit_time>
      <man_months>1</man_months>
      <commits>2</commits>
    </contributor_fact>
    <contributor_fact>
      <contributor_id>2064988064410139</contributor_id>
      <analysis_id>29311198</analysis_id>
      <contributor_name>Yung Siang Liau</contributor_name>
      <primary_language_id>9</primary_language_id>
      <primary_language_nice_name>Python</primary_language_nice_name>
      <comment_ratio />
      <first_commit_time>2014-04-11T00:00:00Z</first_commit_time>
      <last_commit_time>2014-05-22T00:00:00Z</last_commit_time>
      <man_months>2</man_months>
      <commits>2</commits>
    </contributor_fact>
    <contributor_fact>
      <contributor_id>2064988064341763</contributor_id>
      <analysis_id>29311198</analysis_id>
      <contributor_name>Chi Zhang</contributor_name>
      <primary_language_id>9</primary_language_id>
      <primary_language_nice_name>Python</primary_language_nice_name>
      <comment_ratio />
      <first_commit_time>2015-09-01T00:00:00Z</first_commit_time>
      <last_commit_time>2015-09-02T00:00:00Z</last_commit_time>
      <man_months>1</man_months>
      <commits>2</commits>
    </contributor_fact>
    <contributor_fact>
      <contributor_id>2064988064479860</contributor_id>
      <analysis_id>29311198</analysis_id>
      <contributor_name>Will Lamond</contributor_name>
      <primary_language_id>9</primary_language_id>
      <primary_language_nice_name>Python</primary_language_nice_name>
      <comment_ratio />
      <first_commit_time>2014-09-24T00:00:00Z</first_commit_time>
      <last_commit_time>2014-09-27T00:00:00Z</last_commit_time>
      <man_months>1</man_months>
      <commits>2</commits>
    </contributor_fact>
    <contributor_fact>
      <contributor_id>2064988063979475</contributor_id>
      <analysis_id>29311198</analysis_id>
      <contributor_name>Oscar Carlsson</contributor_name>
      <primary_language_id>9</primary_language_id>
      <primary_language_nice_name>Python</primary_language_nice_name>
      <comment_ratio />
      <first_commit_time>2014-03-11T00:00:00Z</first_commit_time>
      <last_commit_time>2014-03-11T00:00:00Z</last_commit_time>
      <man_months>1</man_months>
      <commits>2</commits>
    </contributor_fact>
    <contributor_fact>
      <contributor_id>2064988064359042</contributor_id>
      <analysis_id>29311198</analysis_id>
      <contributor_name>kowalski87</contributor_name>
      <primary_language_id>9</primary_language_id>
      <primary_language_nice_name>Python</primary_language_nice_name>
      <comment_ratio />
      <first_commit_time>2013-12-15T00:00:00Z</first_commit_time>
      <last_commit_time>2013-12-15T00:00:00Z</last_commit_time>
      <man_months>1</man_months>
      <commits>2</commits>
    </contributor_fact>
    <contributor_fact>
      <contributor_id>2064988064530732</contributor_id>
      <analysis_id>29311198</analysis_id>
      <contributor_name>Jack Martin</contributor_name>
      <primary_language_id />
      <primary_language_nice_name />
      <comment_ratio />
      <first_commit_time>2015-03-30T00:00:00Z</first_commit_time>
      <last_commit_time>2015-03-31T00:00:00Z</last_commit_time>
      <man_months>0</man_months>
      <commits>2</commits>
    </contributor_fact>
  </result>
</response>