<response>
  <status>success</status>
  <items_returned>20</items_returned>
  <items_available>76</items_available>
  <first_item_position>20</first_item_position>
  <result>
    <contributor_fact>
      <contributor_id>48380659108894</contributor_id>
      <analysis_id>29221270</analysis_id>
      <contributor_name>srichter</contributor_name>
      <primary_language_id>9</primary_language_id>
      <primary_language_nice_name>Python</primary_language_nice_name>
      <comment_ratio />
      <first_commit_time>2002-12-20T00:00:00Z</first_commit_time>
      <last_commit_time>2008-01-31T00:00:00Z</last_commit_time>
      <man_months>4</man_months>
      <commits>11</commits>
    </contributor_fact>
    <contributor_fact>
      <contributor_id>48380659107312</contributor_id>
      <analysis_id>29221270</analysis_id>
      <contributor_name>klm</contributor_name>
      <primary_language_id>9</primary_language_id>
      <primary_language_nice_name>Python</primary_language_nice_name>
      <comment_ratio />
      <first_commit_time>1999-03-10T00:00:00Z</first_commit_time>
      <last_commit_time>2001-03-28T00:00:00Z</last_commit_time>
      <man_months>7</man_months>
      <commits>11</commits>
    </contributor_fact>
    <contributor_fact>
      <contributor_id>48380659122466</contributor_id>
      <analysis_id>29221270</analysis_id>
      <contributor_name>tlotze</contributor_name>
      <primary_language_id>9</primary_language_id>
      <primary_language_nice_name>Python</primary_language_nice_name>
      <comment_ratio>0.37344398340249</comment_ratio>
      <first_commit_time>2005-11-20T00:00:00Z</first_commit_time>
      <last_commit_time>2009-01-07T00:00:00Z</last_commit_time>
      <man_months>5</man_months>
      <commits>10</commits>
    </contributor_fact>
    <contributor_fact>
      <contributor_id>48380659220863</contributor_id>
      <analysis_id>29221270</analysis_id>
      <contributor_name>patricks</contributor_name>
      <primary_language_id>9</primary_language_id>
      <primary_language_nice_name>Python</primary_language_nice_name>
      <comment_ratio />
      <first_commit_time>2009-08-24T00:00:00Z</first_commit_time>
      <last_commit_time>2010-09-10T00:00:00Z</last_commit_time>
      <man_months>4</man_months>
      <commits>9</commits>
    </contributor_fact>
    <contributor_fact>
      <contributor_id>48378511629122</contributor_id>
      <account_id>6978</account_id>
      <account_name>Martijn Pieters</account_name>
      <analysis_id>29221270</analysis_id>
      <contributor_name>mj</contributor_name>
      <primary_language_id>9</primary_language_id>
      <primary_language_nice_name>Python</primary_language_nice_name>
      <comment_ratio>0.569230769230769</comment_ratio>
      <first_commit_time>2002-08-14T00:00:00Z</first_commit_time>
      <last_commit_time>2005-09-25T00:00:00Z</last_commit_time>
      <man_months>3</man_months>
      <commits>8</commits>
    </contributor_fact>
    <contributor_fact>
      <contributor_id>48378511637169</contributor_id>
      <account_id>15025</account_id>
      <account_name>Florent Guillaume</account_name>
      <analysis_id>29221270</analysis_id>
      <contributor_name>efge</contributor_name>
      <primary_language_id>9</primary_language_id>
      <primary_language_nice_name>Python</primary_language_nice_name>
      <comment_ratio />
      <first_commit_time>2003-01-20T00:00:00Z</first_commit_time>
      <last_commit_time>2006-07-03T00:00:00Z</last_commit_time>
      <man_months>5</man_months>
      <commits>7</commits>
    </contributor_fact>
    <contributor_fact>
      <contributor_id>48380659106886</contributor_id>
      <analysis_id>29221270</analysis_id>
      <contributor_name>matt</contributor_name>
      <primary_language_id>42</primary_language_id>
      <primary_language_nice_name>C</primary_language_nice_name>
      <comment_ratio>0.80064308681672</comment_ratio>
      <first_commit_time>2001-06-20T00:00:00Z</first_commit_time>
      <last_commit_time>2002-01-24T00:00:00Z</last_commit_time>
      <man_months>4</man_months>
      <commits>7</commits>
    </contributor_fact>
    <contributor_fact>
      <contributor_id>48380659132858</contributor_id>
      <analysis_id>29221270</analysis_id>
      <contributor_name>benji_york</contributor_name>
      <primary_language_id>42</primary_language_id>
      <primary_language_nice_name>C</primary_language_nice_name>
      <comment_ratio />
      <first_commit_time>2005-09-05T00:00:00Z</first_commit_time>
      <last_commit_time>2009-09-01T00:00:00Z</last_commit_time>
      <man_months>4</man_months>
      <commits>6</commits>
    </contributor_fact>
    <contributor_fact>
      <contributor_id>48380659121458</contributor_id>
      <analysis_id>29221270</analysis_id>
      <contributor_name>spascoe</contributor_name>
      <primary_language_id>42</primary_language_id>
      <primary_language_nice_name>C</primary_language_nice_name>
      <comment_ratio />
      <first_commit_time>2004-05-01T00:00:00Z</first_commit_time>
      <last_commit_time>2004-05-03T00:00:00Z</last_commit_time>
      <man_months>1</man_months>
      <commits>5</commits>
    </contributor_fact>
    <contributor_fact>
      <contributor_id>48378511641458</contributor_id>
      <account_id>19314</account_id>
      <account_name>cjw296</account_name>
      <analysis_id>29221270</analysis_id>
      <contributor_name>chrisw</contributor_name>
      <primary_language_id>9</primary_language_id>
      <primary_language_nice_name>Python</primary_language_nice_name>
      <comment_ratio />
      <first_commit_time>2002-04-15T00:00:00Z</first_commit_time>
      <last_commit_time>2009-11-19T00:00:00Z</last_commit_time>
      <man_months>5</man_months>
      <commits>5</commits>
    </contributor_fact>
    <contributor_fact>
      <contributor_id>48380659161687</contributor_id>
      <analysis_id>29221270</analysis_id>
      <contributor_name>davisagli</contributor_name>
      <primary_language_id>9</primary_language_id>
      <primary_language_nice_name>Python</primary_language_nice_name>
      <comment_ratio>0.0289855072463768</comment_ratio>
      <first_commit_time>2011-04-14T00:00:00Z</first_commit_time>
      <last_commit_time>2011-04-15T00:00:00Z</last_commit_time>
      <man_months>1</man_months>
      <commits>5</commits>
    </contributor_fact>
    <contributor_fact>
      <contributor_id>48378511640333</contributor_id>
      <account_id>18189</account_id>
      <account_name>Philipp von Weitershausen</account_name>
      <analysis_id>29221270</analysis_id>
      <contributor_name>philikon</contributor_name>
      <primary_language_id>9</primary_language_id>
      <primary_language_nice_name>Python</primary_language_nice_name>
      <comment_ratio />
      <first_commit_time>2004-02-27T00:00:00Z</first_commit_time>
      <last_commit_time>2007-11-10T00:00:00Z</last_commit_time>
      <man_months>2</man_months>
      <commits>5</commits>
    </contributor_fact>
    <contributor_fact>
      <contributor_id>48380659107279</contributor_id>
      <analysis_id>29221270</analysis_id>
      <contributor_name>pje</contributor_name>
      <primary_language_id>37</primary_language_id>
      <primary_language_nice_name>TeX/LaTeX</primary_language_nice_name>
      <comment_ratio />
      <first_commit_time>2003-04-21T00:00:00Z</first_commit_time>
      <last_commit_time>2003-11-26T00:00:00Z</last_commit_time>
      <man_months>2</man_months>
      <commits>4</commits>
    </contributor_fact>
    <contributor_fact>
      <contributor_id>48380659108775</contributor_id>
      <analysis_id>29221270</analysis_id>
      <contributor_name>anguenot</contributor_name>
      <primary_language_id>9</primary_language_id>
      <primary_language_nice_name>Python</primary_language_nice_name>
      <comment_ratio />
      <first_commit_time>2005-09-30T00:00:00Z</first_commit_time>
      <last_commit_time>2006-01-05T00:00:00Z</last_commit_time>
      <man_months>2</man_months>
      <commits>4</commits>
    </contributor_fact>
    <contributor_fact>
      <contributor_id>48380659108770</contributor_id>
      <analysis_id>29221270</analysis_id>
      <contributor_name>caseman</contributor_name>
      <primary_language_id>9</primary_language_id>
      <primary_language_nice_name>Python</primary_language_nice_name>
      <comment_ratio />
      <first_commit_time>2002-09-13T00:00:00Z</first_commit_time>
      <last_commit_time>2004-06-02T00:00:00Z</last_commit_time>
      <man_months>2</man_months>
      <commits>4</commits>
    </contributor_fact>
    <contributor_fact>
      <contributor_id>48380659108879</contributor_id>
      <analysis_id>29221270</analysis_id>
      <contributor_name>michel</contributor_name>
      <primary_language_id>9</primary_language_id>
      <primary_language_nice_name>Python</primary_language_nice_name>
      <comment_ratio />
      <first_commit_time>1999-08-04T00:00:00Z</first_commit_time>
      <last_commit_time>2000-03-22T00:00:00Z</last_commit_time>
      <man_months>2</man_months>
      <commits>4</commits>
    </contributor_fact>
    <contributor_fact>
      <contributor_id>48378511627268</contributor_id>
      <account_id>5124</account_id>
      <account_name>zagy</account_name>
      <analysis_id>29221270</analysis_id>
      <contributor_name>zagy</contributor_name>
      <primary_language_id>9</primary_language_id>
      <primary_language_nice_name>Python</primary_language_nice_name>
      <comment_ratio />
      <first_commit_time>2008-06-05T00:00:00Z</first_commit_time>
      <last_commit_time>2010-06-14T00:00:00Z</last_commit_time>
      <man_months>1</man_months>
      <commits>4</commits>
    </contributor_fact>
    <contributor_fact>
      <contributor_id>48380659107626</contributor_id>
      <analysis_id>29221270</analysis_id>
      <contributor_name>richard</contributor_name>
      <primary_language_id>3</primary_language_id>
      <primary_language_nice_name>XML</primary_language_nice_name>
      <comment_ratio />
      <first_commit_time>2003-04-03T00:00:00Z</first_commit_time>
      <last_commit_time>2003-06-02T00:00:00Z</last_commit_time>
      <man_months>2</man_months>
      <commits>4</commits>
    </contributor_fact>
    <contributor_fact>
      <contributor_id>48380659113717</contributor_id>
      <analysis_id>29221270</analysis_id>
      <contributor_name>ccomb</contributor_name>
      <primary_language_id>9</primary_language_id>
      <primary_language_nice_name>Python</primary_language_nice_name>
      <comment_ratio />
      <first_commit_time>2008-10-11T00:00:00Z</first_commit_time>
      <last_commit_time>2008-10-13T00:00:00Z</last_commit_time>
      <man_months>1</man_months>
      <commits>4</commits>
    </contributor_fact>
    <contributor_fact>
      <contributor_id>48378511717664</contributor_id>
      <account_id>95520</account_id>
      <account_name>Michael Howitz</account_name>
      <analysis_id>29221270</analysis_id>
      <contributor_name>icemac</contributor_name>
      <primary_language_id>9</primary_language_id>
      <primary_language_nice_name>Python</primary_language_nice_name>
      <comment_ratio />
      <first_commit_time>2008-09-23T00:00:00Z</first_commit_time>
      <last_commit_time>2008-09-23T00:00:00Z</last_commit_time>
      <man_months>1</man_months>
      <commits>3</commits>
    </contributor_fact>
  </result>
</response>