<response>
  <status>success</status>
  <items_returned>13</items_returned>
  <items_available>73</items_available>
  <first_item_position>60</first_item_position>
  <result>
    <contributor_fact>
      <contributor_id>2069368931187596</contributor_id>
      <analysis_id>29304724</analysis_id>
      <contributor_name>anca</contributor_name>
      <primary_language_id>44</primary_language_id>
      <primary_language_nice_name>C++</primary_language_nice_name>
      <comment_ratio>0.319144518272425</comment_ratio>
      <first_commit_time>2015-01-10T00:00:00Z</first_commit_time>
      <last_commit_time>2015-01-10T00:00:00Z</last_commit_time>
      <man_months>1</man_months>
      <commits>1</commits>
    </contributor_fact>
    <contributor_fact>
      <contributor_id>2069368931094349</contributor_id>
      <analysis_id>29304724</analysis_id>
      <contributor_name>Paul van Maaren</contributor_name>
      <primary_language_id>44</primary_language_id>
      <primary_language_nice_name>C++</primary_language_nice_name>
      <comment_ratio />
      <first_commit_time>2014-06-20T00:00:00Z</first_commit_time>
      <last_commit_time>2014-06-20T00:00:00Z</last_commit_time>
      <man_months>1</man_months>
      <commits>1</commits>
    </contributor_fact>
    <contributor_fact>
      <contributor_id>2069368930840365</contributor_id>
      <analysis_id>29304724</analysis_id>
      <contributor_name>Bogdan Iorga</contributor_name>
      <primary_language_id />
      <primary_language_nice_name />
      <comment_ratio />
      <first_commit_time>2012-08-22T00:00:00Z</first_commit_time>
      <last_commit_time>2012-08-22T00:00:00Z</last_commit_time>
      <man_months>0</man_months>
      <commits>1</commits>
    </contributor_fact>
    <contributor_fact>
      <contributor_id>2069368930587169</contributor_id>
      <analysis_id>29304724</analysis_id>
      <contributor_name>toonen</contributor_name>
      <primary_language_id>42</primary_language_id>
      <primary_language_nice_name>C</primary_language_nice_name>
      <comment_ratio />
      <first_commit_time>1998-04-08T00:00:00Z</first_commit_time>
      <last_commit_time>1998-04-08T00:00:00Z</last_commit_time>
      <man_months>1</man_months>
      <commits>1</commits>
    </contributor_fact>
    <contributor_fact>
      <contributor_id>2069368931116271</contributor_id>
      <analysis_id>29304724</analysis_id>
      <contributor_name>Stefan Fleischmann</contributor_name>
      <primary_language_id>42</primary_language_id>
      <primary_language_nice_name>C</primary_language_nice_name>
      <comment_ratio />
      <first_commit_time>2014-08-08T00:00:00Z</first_commit_time>
      <last_commit_time>2014-08-08T00:00:00Z</last_commit_time>
      <man_months>1</man_months>
      <commits>1</commits>
    </contributor_fact>
    <contributor_fact>
      <contributor_id>2069368930980644</contributor_id>
      <analysis_id>29304724</analysis_id>
      <contributor_name>Matthew Harrigan</contributor_name>
      <primary_language_id>44</primary_language_id>
      <primary_language_nice_name>C++</primary_language_nice_name>
      <comment_ratio />
      <first_commit_time>2016-02-12T00:00:00Z</first_commit_time>
      <last_commit_time>2016-02-12T00:00:00Z</last_commit_time>
      <man_months>1</man_months>
      <commits>1</commits>
    </contributor_fact>
    <contributor_fact>
      <contributor_id>2069366782836304</contributor_id>
      <account_id>15952</account_id>
      <account_name>Pino Toscano</account_name>
      <analysis_id>29304724</analysis_id>
      <contributor_name>Pino Toscano</contributor_name>
      <primary_language_id>74</primary_language_id>
      <primary_language_nice_name>CMake</primary_language_nice_name>
      <comment_ratio />
      <first_commit_time>2014-05-05T00:00:00Z</first_commit_time>
      <last_commit_time>2014-05-05T00:00:00Z</last_commit_time>
      <man_months>1</man_months>
      <commits>1</commits>
    </contributor_fact>
    <contributor_fact>
      <contributor_id>2069368931137148</contributor_id>
      <analysis_id>29304724</analysis_id>
      <contributor_name>Jiri Kraus</contributor_name>
      <primary_language_id>84</primary_language_id>
      <primary_language_nice_name>CUDA</primary_language_nice_name>
      <comment_ratio>0.360215053763441</comment_ratio>
      <first_commit_time>2014-10-22T00:00:00Z</first_commit_time>
      <last_commit_time>2014-10-22T00:00:00Z</last_commit_time>
      <man_months>1</man_months>
      <commits>1</commits>
    </contributor_fact>
    <contributor_fact>
      <contributor_id>2069368930482121</contributor_id>
      <analysis_id>29304724</analysis_id>
      <contributor_name>Olivier Fisette</contributor_name>
      <primary_language_id>44</primary_language_id>
      <primary_language_nice_name>C++</primary_language_nice_name>
      <comment_ratio />
      <first_commit_time>2015-04-26T00:00:00Z</first_commit_time>
      <last_commit_time>2015-04-26T00:00:00Z</last_commit_time>
      <man_months>1</man_months>
      <commits>1</commits>
    </contributor_fact>
    <contributor_fact>
      <contributor_id>2069368931245559</contributor_id>
      <analysis_id>29304724</analysis_id>
      <contributor_name>Ansgar Esztermann</contributor_name>
      <primary_language_id>42</primary_language_id>
      <primary_language_nice_name>C</primary_language_nice_name>
      <comment_ratio />
      <first_commit_time>2016-01-20T00:00:00Z</first_commit_time>
      <last_commit_time>2016-01-20T00:00:00Z</last_commit_time>
      <man_months>1</man_months>
      <commits>1</commits>
    </contributor_fact>
    <contributor_fact>
      <contributor_id>2069368930928073</contributor_id>
      <analysis_id>29304724</analysis_id>
      <contributor_name>P S Lacerda</contributor_name>
      <primary_language_id>42</primary_language_id>
      <primary_language_nice_name>C</primary_language_nice_name>
      <comment_ratio />
      <first_commit_time>2013-05-17T00:00:00Z</first_commit_time>
      <last_commit_time>2013-05-17T00:00:00Z</last_commit_time>
      <man_months>1</man_months>
      <commits>1</commits>
    </contributor_fact>
    <contributor_fact>
      <contributor_id>2069366782935586</contributor_id>
      <account_id>115234</account_id>
      <account_name>Tristan Bereau</account_name>
      <analysis_id>0</analysis_id>
      <contributor_name />
      <primary_language_id>0</primary_language_id>
      <primary_language_nice_name />
      <comment_ratio>0</comment_ratio>
      <first_commit_time />
      <last_commit_time />
      <man_months>0</man_months>
      <commits>0</commits>
    </contributor_fact>
    <contributor_fact>
      <contributor_id>2069366782980468</contributor_id>
      <account_id>160116</account_id>
      <account_name>praprot</account_name>
      <analysis_id>0</analysis_id>
      <contributor_name />
      <primary_language_id>0</primary_language_id>
      <primary_language_nice_name />
      <comment_ratio>0</comment_ratio>
      <first_commit_time />
      <last_commit_time />
      <man_months>0</man_months>
      <commits>0</commits>
    </contributor_fact>
  </result>
</response>